[
    {
        "category": "science",
        "id": "647f9da63a4302a7192715db",
        "correctAnswer": "Open and Closed",
        "incorrectAnswers": [
            "Curved and Straight",
            "Hairline and Fault line ",
            "Partial and Complete"
        ],
        "question": {
            "text": "What are the two main types of bone fracture?"
        },
        "tags": [
            "anatomy",
            "medicine",
            "science",
            "biology",
            "bones"
        ],
        "type": "text_choice",
        "difficulty": "medium",
        "regions": [],
        "isNiche": false
    },
    {
        "category": "sport_and_leisure",
        "id": "65056eff7a97013de78b53ab",
        "correctAnswer": "Eel fishing",
        "incorrectAnswers": [
            "Bear hunting",
            "Hawking",
            "Crabbing"
        ],
        "question": {
            "text": "What are you doing when you are sniggling?"
        },
        "tags": [
            "sport_and_leisure"
        ],
        "type": "text_choice",
        "difficulty": "hard",
        "regions": [],
        "isNiche": false
    },
    {
        "category": "society_and_culture",
        "id": "639c9dab929b90846f2fc989",
        "correctAnswer": "Hajj",
        "incorrectAnswers": [
            "Umrah",
            "Haram",
            "Ziyarat"
        ],
        "question": {
            "text": "What is the name for the Islamic pilgrimage to Mecca?"
        },
        "tags": [
            "islam",
            "religion",
            "society_and_culture",
            "traditions"
        ],
        "type": "text_choice",
        "difficulty": "medium",
        "regions": [],
        "isNiche": false
    },
    {
        "category": "music",
        "id": "622a1c387cc59eab6f950b7b",
        "correctAnswer": "Modern Talking",
        "incorrectAnswers": [
            "Sodom",
            "Rage",
            "Edguy"
        ],
        "question": {
            "text": "Which German synth pop duo released the song 'You're My Heart, You're My Soul'?"
        },
        "tags": [
            "music"
        ],
        "type": "text_choice",
        "difficulty": "hard",
        "regions": [],
        "isNiche": false
    },
    {
        "category": "film_and_tv",
        "id": "622a1c347cc59eab6f94f8ba",
        "correctAnswer": "Anthony Perkins",
        "incorrectAnswers": [
            "Orson Welles",
            "Andy Serkis",
            "Robert Duvall"
        ],
        "question": {
            "text": "Which actor played the role of Norman Bates in Psycho?"
        },
        "tags": [
            "film",
            "acting",
            "film_and_tv"
        ],
        "type": "text_choice",
        "difficulty": "hard",
        "regions": [],
        "isNiche": false
    },
    {
        "category": "geography",
        "id": "62374300cb85f7ce9e949e07",
        "correctAnswer": "Zimbabwe",
        "incorrectAnswers": [
            "Namibia",
            "Malaysia",
            "Belgium"
        ],
        "question": {
            "text": "Harare is the capital city of which country?"
        },
        "tags": [
            "geography"
        ],
        "type": "text_choice",
        "difficulty": "hard",
        "regions": [],
        "isNiche": false
    },
    {
        "category": "science",
        "id": "6243351bcfaae40c12961486",
        "correctAnswer": "A Buck",
        "incorrectAnswers": [
            "A Jack",
            "A Billy",
            "A Drake"
        ],
        "question": {
            "text": "What is a male rat known as?"
        },
        "tags": [
            "science"
        ],
        "type": "text_choice",
        "difficulty": "hard",
        "regions": [],
        "isNiche": false
    },
    {
        "category": "geography",
        "id": "625e9fa4796f721e95543fac",
        "correctAnswer": "White",
        "incorrectAnswers": [
            "Red",
            "Green",
            "Blue"
        ],
        "question": {
            "text": "Which of these colors is included on the flag of Qatar?"
        },
        "tags": [
            "flags",
            "geography"
        ],
        "type": "text_choice",
        "difficulty": "hard",
        "regions": [],
        "isNiche": false
    },
    {
        "category": "science",
        "id": "6242cb51d543524f1b19c922",
        "correctAnswer": "A kindle",
        "incorrectAnswers": [
            "A gang",
            "A stud",
            "A fall"
        ],
        "question": {
            "text": "What is the word for a group of kittens?"
        },
        "tags": [
            "science"
        ],
        "type": "text_choice",
        "difficulty": "hard",
        "regions": [],
        "isNiche": false
    },
    {
        "category": "history",
        "id": "622a1c3c7cc59eab6f951874",
        "correctAnswer": "800BC",
        "incorrectAnswers": [
            "2000BC",
            "50BC",
            "200AD"
        ],
        "question": {
            "text": "When was the Greek alphabet first used?"
        },
        "tags": [
            "ancient_greece",
            "language",
            "the_ancient_world",
            "history"
        ],
        "type": "text_choice",
        "difficulty": "medium",
        "regions": [],
        "isNiche": false
    }
]